ezsub/__init__.py
ezsub/cache.py
ezsub/conf.py
ezsub/const.py
ezsub/destination.py
ezsub/errors.py
ezsub/mirrors.py
ezsub/utils.py
ezsub/cli/__init__.py
ezsub/cli/arguments.py
ezsub/cli/commands/__init__.py
ezsub/cli/commands/backup.py
ezsub/cli/commands/clean.py
ezsub/cli/commands/config.py
ezsub/cli/commands/download.py
ezsub/cli/commands/history.py
ezsub/cli/commands/info.py
ezsub/cli/commands/login.py
ezsub/cli/commands/unzip.py
ezsub/cli/commands/update.py
ezsub-2021.9.7.dist-info/LICENSE
ezsub-2021.9.7.dist-info/METADATA
ezsub-2021.9.7.dist-info/WHEEL
ezsub-2021.9.7.dist-info/entry_points.txt
ezsub-2021.9.7.dist-info/top_level.txt
ezsub-2021.9.7.dist-info/RECORD
