Metadata-Version: 2.1
Name: ezsub
Version: 2021.9.7
Summary: Download subtitle from subscene
Home-page: http://github.com/7aman/ezsub
Author: Zaman
Author-email: 7amaaan@gmail.com
License: MIT
Project-URL: source, http://github.com/7aman/ezsub
Keywords: subtitle movie subscene
Platform: UNKNOWN
Classifier: Programming Language :: Python :: 3 :: Only
Classifier: Development Status :: 5 - Production/Stable
Classifier: Operating System :: POSIX :: Linux
Classifier: Environment :: Console
Classifier: Intended Audience :: End Users/Desktop
Classifier: License :: OSI Approved :: MIT License
Classifier: Natural Language :: English
Classifier: Topic :: Utilities
Requires-Python: >=3.7
Requires-Dist: bs4
Requires-Dist: requests-futures
Requires-Dist: rarfile
